clepy
