Metadata-Version: 1.0
Name: clepy
Version: 0.3.23
Summary: utilities from the Cleveland Python user group
Home-page: http://code.google.com/p/clepy
Author: W. Matthew Wilson
Author-email: matt@216software.com
License: MIT License
Platform: UNKNOWN
